{
    "key": "group_670bbe1dd2210",
    "title": "Financial Statistics Block",
    "fields": [
        {
            "key": "field_670d866ba6710",
            "label": "Title",
            "name": "title",
            "aria-label": "",
            "type": "text",
            "instructions": "",
            "required": 0,
            "conditional_logic": 0,
            "wrapper": {
                "width": "",
                "class": "",
                "id": ""
            },
            "default_value": "",
            "maxlength": "",
            "allow_in_bindings": 0,
            "placeholder": "",
            "prepend": "",
            "append": ""
        },
        {
            "key": "field_670a3a2078a79",
            "label": "Metric 1 Title",
            "name": "metric_1_title",
            "aria-label": "",
            "type": "text",
            "instructions": "",
            "required": 0,
            "conditional_logic": 0,
            "wrapper": {
                "width": "",
                "class": "",
                "id": ""
            },
            "default_value": "",
            "maxlength": "",
            "allow_in_bindings": 0,
            "placeholder": "",
            "prepend": "",
            "append": ""
        },
        {
            "key": "field_670a3acb78a7a",
            "label": "Metric 1 Value",
            "name": "metric_1_value",
            "aria-label": "",
            "type": "number",
            "instructions": "",
            "required": 0,
            "conditional_logic": 0,
            "wrapper": {
                "width": "",
                "class": "",
                "id": ""
            },
            "default_value": "",
            "min": "",
            "max": "",
            "allow_in_bindings": 0,
            "placeholder": "",
            "step": "",
            "prepend": "",
            "append": ""
        },
        {
            "key": "field_670a3ade78a7b",
            "label": "Metric 2 Title",
            "name": "metric_2_title",
            "aria-label": "",
            "type": "text",
            "instructions": "",
            "required": 0,
            "conditional_logic": 0,
            "wrapper": {
                "width": "",
                "class": "",
                "id": ""
            },
            "default_value": "",
            "maxlength": "",
            "allow_in_bindings": 0,
            "placeholder": "",
            "prepend": "",
            "append": ""
        },
        {
            "key": "field_670a3af278a7c",
            "label": "Metric 2 Value",
            "name": "metric_2_value",
            "aria-label": "",
            "type": "number",
            "instructions": "",
            "required": 0,
            "conditional_logic": 0,
            "wrapper": {
                "width": "",
                "class": "",
                "id": ""
            },
            "default_value": "",
            "min": "",
            "max": "",
            "allow_in_bindings": 0,
            "placeholder": "",
            "step": "",
            "prepend": "",
            "append": ""
        },
        {
            "key": "field_670a3b0278a7d",
            "label": "Metric 3 Title",
            "name": "metric_3_title",
            "aria-label": "",
            "type": "text",
            "instructions": "",
            "required": 0,
            "conditional_logic": 0,
            "wrapper": {
                "width": "",
                "class": "",
                "id": ""
            },
            "default_value": "",
            "maxlength": "",
            "allow_in_bindings": 0,
            "placeholder": "",
            "prepend": "",
            "append": ""
        },
        {
            "key": "field_670a3b0f78a7e",
            "label": "Metric 3 Value",
            "name": "metric_3_value",
            "aria-label": "",
            "type": "number",
            "instructions": "",
            "required": 0,
            "conditional_logic": 0,
            "wrapper": {
                "width": "",
                "class": "",
                "id": ""
            },
            "default_value": "",
            "min": "",
            "max": "",
            "allow_in_bindings": 0,
            "placeholder": "",
            "step": "",
            "prepend": "",
            "append": ""
        },
        {
            "key": "field_670a3b1d78a7f",
            "label": "Description",
            "name": "description",
            "aria-label": "",
            "type": "textarea",
            "instructions": "",
            "required": 0,
            "conditional_logic": 0,
            "wrapper": {
                "width": "",
                "class": "",
                "id": ""
            },
            "default_value": "",
            "maxlength": "",
            "allow_in_bindings": 0,
            "rows": "",
            "placeholder": "",
            "new_lines": ""
        }
    ],
    "location": [
        [
            {
                "param": "block",
                "operator": "==",
                "value": "acf\/financial-statistics"
            }
        ]
    ],
    "menu_order": 0,
    "position": "normal",
    "style": "default",
    "label_placement": "top",
    "instruction_placement": "label",
    "hide_on_screen": "",
    "active": true,
    "description": "",
    "show_in_rest": 0,
    "modified": 1728940433
}
